lastfm_monitor.py
lastfm_monitor-2.3.dist-info/licenses/LICENSE
lastfm_monitor-2.3.dist-info/METADATA
lastfm_monitor-2.3.dist-info/WHEEL
lastfm_monitor-2.3.dist-info/entry_points.txt
lastfm_monitor-2.3.dist-info/top_level.txt
lastfm_monitor-2.3.dist-info/RECORD
