Metadata-Version: 2.4
Name: lastfm_monitor
Version: 2.3
Summary: Tool implementing real-time tracking of Last.fm users music activity
Author-email: Michal Szymanski <misiektoja-pypi@rm-rf.ninja>
License-Expression: GPL-3.0-or-later
Project-URL: Homepage, https://github.com/misiektoja/lastfm_monitor
Project-URL: Source, https://github.com/misiektoja/lastfm_monitor
Project-URL: Changelog, https://github.com/misiektoja/lastfm_monitor/blob/main/RELEASE_NOTES.md
Keywords: lastfm,monitoring,tracking,real-time,osint,pylast,spotipy
Classifier: Programming Language :: Python :: 3
Classifier: Operating System :: OS Independent
Classifier: Operating System :: Microsoft :: Windows
Classifier: Operating System :: POSIX :: Linux
Classifier: Operating System :: MacOS :: MacOS X
Requires-Python: >=3.9
License-File: LICENSE
Requires-Dist: pylast>=5.2.0
Requires-Dist: requests>=2.0
Requires-Dist: python-dateutil>=2.8
Requires-Dist: spotipy>=2.24.0
Requires-Dist: python-dotenv>=0.19
Dynamic: license-file
